tartanair/__init__.py
tartanair/convert_seg_label.py
tartanair/customizer.py
tartanair/dataloader.py
tartanair/dataset.py
tartanair/download_files.txt
tartanair/download_ground_files.txt
tartanair/downloader.py
tartanair/evaluator.py
tartanair/flow_calculation.py
tartanair/flow_utils.py
tartanair/iterator.py
tartanair/lister.py
tartanair/random_accessor.py
tartanair/reader.py
tartanair/seg_label.json
tartanair/seg_label_map.json
tartanair/seg_rgbs.txt
tartanair/tartanair.py
tartanair/tartanair_module.py
tartanair/visualizer.py
tartanair/data_cacher/.git
tartanair/data_cacher/CacherDataset.py
tartanair/data_cacher/ConfigParser.py
tartanair/data_cacher/DataCacher.py
tartanair/data_cacher/DataSplitter.py
tartanair/data_cacher/LICENSE
tartanair/data_cacher/MapDict.py
tartanair/data_cacher/MultiDatasets.py
tartanair/data_cacher/RAMBuffer.py
tartanair/data_cacher/RAMDataset.py
tartanair/data_cacher/README.md
tartanair/data_cacher/TrajBuffer.py
tartanair/data_cacher/__init__.py
tartanair/data_cacher/data_roots.py
tartanair/data_cacher/datafile_editor.py
tartanair/data_cacher/example_datacacher.py
tartanair/data_cacher/example_multidatasets.py
tartanair/data_cacher/example_multidatasets_blinkflow.py
tartanair/data_cacher/o3d_camera.npz
tartanair/data_cacher/seg_rgbs.txt
tartanair/data_cacher/utils.py
tartanair/data_cacher/data/data_tartanairv2.txt
tartanair/data_cacher/data/event_test.txt
tartanair/data_cacher/data/event_test_blinkflow.txt
tartanair/data_cacher/data/event_test_tartanairv2.txt
tartanair/data_cacher/data/event_train_blinkflow.txt
tartanair/data_cacher/data/event_train_tartanairv2.txt
tartanair/data_cacher/data/tartan_test.txt
tartanair/data_cacher/data/tartan_train.txt
tartanair/data_cacher/data/test_datafile.txt
tartanair/data_cacher/dataspec/flowvo_train_local_v1.yaml
tartanair/data_cacher/dataspec/flowvo_train_local_v2.yaml
tartanair/data_cacher/dataspec/sample_tartanair_random.yaml
tartanair/data_cacher/dataspec/sample_tartanair_test.yaml
tartanair-1.2.0.dist-info/METADATA
tartanair-1.2.0.dist-info/WHEEL
tartanair-1.2.0.dist-info/licenses/LICENSE
tartanair-1.2.0.dist-info/RECORD
