Metadata-Version: 2.4
Name: tartanair
Version: 1.2.0
Summary: TartanAir
Project-URL: Homepage, https://tartanair.org
Author-email: Yorai Shaoul <yorai@cmu.edu>, Yuchen Zhang <yuchenz7@andrew.cmu.edu>, Yaoyu Hu <yaoyuh@andrew.cmu.edu>, Wenshan Wang <wenshanw@andrew.cmu.edu>
License-File: LICENSE
Classifier: License :: OSI Approved :: MIT License
Classifier: Operating System :: OS Independent
Classifier: Programming Language :: Python :: 3
Requires-Python: >=3.7
Requires-Dist: boto3
Requires-Dist: colorama>=0.4.0
Requires-Dist: cupy-cuda12x
Requires-Dist: einops
Requires-Dist: imageio
Requires-Dist: kornia
Requires-Dist: matplotlib>=3.1.2
Requires-Dist: minio
Requires-Dist: networkx>=2.4
Requires-Dist: numba>=0.56
Requires-Dist: numpy
Requires-Dist: opencv-contrib-python
Requires-Dist: pandas
Requires-Dist: pillow
Requires-Dist: plyfile
Requires-Dist: pyquaternion
Requires-Dist: pytransform3d
Requires-Dist: pyyaml
Requires-Dist: scipy
Requires-Dist: torch
Requires-Dist: torchvision
Requires-Dist: tqdm
